{
  "items": [
    {
      "name": "DenGraur",
      "id": 20620,
      "uniqueUrlName": null,
      "photos": {
        "small": null,
        "large": null
      },
      "status": null,
      "followed": false
    },
    {
      "name": "SpanDetectea",
      "id": 20619,
      "uniqueUrlName": null,
      "photos": {
        "small": null,
        "large": null
      },
      "status": null,
      "followed": false
    },
    {
      "name": "Triumphant",
      "id": 20618,
      "uniqueUrlName": null,
      "photos": {
        "small": null,
        "large": null
      },
      "status": null,
      "followed": false
    },
    {
      "name": "leather_man777",
      "id": 20617,
      "uniqueUrlName": null,
      "photos": {
        "small": null,
        "large": null
      },
      "status": null,
      "followed": false
    },
    {
      "name": "leather_man666",
      "id": 20616,
      "uniqueUrlName": null,
      "photos": {
        "small": null,
        "large": null
      },
      "status": null,
      "followed": false
    },
    {
      "name": "tuberkulbek",
      "id": 20615,
      "uniqueUrlName": null,
      "photos": {
        "small": null,
        "large": null
      },
      "status": null,
      "followed": false
    },
    {
      "name": "yahoo66x",
      "id": 20614,
      "uniqueUrlName": null,
      "photos": {
        "small": null,
        "large": null
      },
      "status": null,
      "followed": false
    },
    {
      "name": "vadzimka0",
      "id": 20613,
      "uniqueUrlName": null,
      "photos": {
        "small": null,
        "large": null
      },
      "status": null,
      "followed": false
    },
    {
      "name": "AltV",
      "id": 20612,
      "uniqueUrlName": null,
      "photos": {
        "small": null,
        "large": null
      },
      "status": null,
      "followed": false
    },
    {
      "name": "gbpljc",
      "id": 20611,
      "uniqueUrlName": null,
      "photos": {
        "small": null,
        "large": null
      },
      "status": null,
      "followed": false
    }
  ],
  "totalCount": 15628,
  "error": null
}
